{
  "PANCH-MAHAPURUSHA-YOGAS": "पंच महा पुरुष योग",
  "NABHASA-YOGAS": "नाभासा योग",
  "AASHRAYA-YOGAS": "आश्रय योग",
  "DALA-YOGAS": "दल योग",
  "AAKRITI-YOGAS": "आकृति योग",
  "SANKHYA-YOGAS": "संख्या योग",
  "CHANDRA-YOGAS": "चंद्र योगायें",
  "RAVI-YOGAS": "रवि योगायें",
  "GADA-YOGAS": "गड योग",
  "PARIVARTHANA-YOGAS": "परिवर्तन योगों ",
  "UBAHAYACHARI-YOGA": " उभयचरी योग",
  "VESHI-YOGA": "वेशी योग",
  "VOSHI-YOGA": "वोशि योग",
  "RUCHAKA-YOGA": "रुचका योग",
  "BHADRA-YOGA": "भाद्र योग",
  "HAMSA-YOGA": "हंसा योग",
  "MALVA-YOGA": "मालवा योग",
  "SHASHA-YOGA": "शाशा योग",
  "GAJKESRI-YOGA": "गजकेसरी योग",
  "ADHI-YOGA": "आधी योग",
  "DURUDHARA-YOGA": "दुरुधरा योग",
  "SUNAPHA-YOGA": "सुनफा योग",
  "ANAPHA-YOGA": "अनफा योग",
  "VASUMAN-YOGA": "वासुमान योग",
  "UTTAMADI-YOGA": "उत्तामादि योग",
  "SHAKATA-YOGA": "शकता योग",
  "PAKSHI-YOGA": "पक्षी योग",
  "LAGNAHI-YOGA": "लग्नही योग",
  "VEENA-YOGA": "वीणा योग",
  "DAAMA-YOGA": "दाम योग",
  "PAASHA-YOGA": "पाशा योग",
  "KEDHARA-YOGA": "केधार योग",
  "SHOOLA-YOGA": "शूला योग",
  "YUGA-YOGA": "युग योग",
  "GOLA-YOGA": "गोला योग",
  "RAJJU-YOGA": "रज्जु योग",
  "MUSALA-YOGA": "मुसला योग",
  "NALA-YOGA": "नाला योग",
  "MAALA-YOGA": "माला योग",
  "SARPA-YOGA": "सर्प योग",
  "SHANKHA-YOGA": "शंख योग",
  "VIBHUKA-YOGA": "",
  "DHWAJA-YOGA": "ध्वजा योग",
  "MAHA-YOGA": "महा योग",
  "KHADGA-YOGA": "खड्ग योग",
  "VAJRA-YOGA": "वज्र योग",
  "KAMALA-YOGA": "कमला योग",
  "PARVATA-YOGA": "पर्वत योग",
  "KAAHALA-YOGA": "खःला योग",
  "CHAAMARA-YOGA": "चमरा योग",
  "BHERI-YOGA": "भेरी योग",
  "VAPI-YOGA": "वापी योग",
  "SHRINGATAKA-YOGA": "शृंगाटक योग",
  "HALA-YOGA": "हाला योग",
  "LAKSHMI-YOGA": "लक्ष्मी योग",
  "KEMADRUMA-YOGA": "केमद्रुम योग"
}