{"moduleName":null,"summaries":[{"symbol":{"__symbol":0,"members":[]},"metadata":{"__symbolic":"class","members":{"divChart":[{"__symbolic":"property","decorators":[{"__symbolic":"call","expression":{"__symbol":1,"members":[]},"arguments":["divChart"]}]}],"__ctor__":[{"__symbolic":"constructor","parameters":[{"__symbol":2,"members":[]},{"__symbol":3,"members":[]},{"__symbol":4,"members":[]},{"__symbol":5,"members":[]},{"__symbol":6,"members":[]},{"__symbol":7,"members":[]},{"__symbol":8,"members":[]}]}],"ionViewDidLoad":[{"__symbolic":"method"}],"ngOnDestroy":[{"__symbolic":"method"}],"calcHoraChart":[{"__symbolic":"method"}],"calcDivChart":[{"__symbolic":"method"}],"updateNodePos":[{"__symbolic":"method"}],"updateAsc":[{"__symbolic":"method"}],"loadHoro":[{"__symbolic":"method"}],"grid":[{"__symbolic":"method"}],"logElement":[{"__symbolic":"method"}]}},"type":{"summaryKind":1,"type":{"reference":{"__symbol":0,"members":[]},"diDeps":[{"isAttribute":false,"isHost":false,"isSelf":false,"isSkipSelf":false,"isOptional":false,"token":{"identifier":{"reference":{"__symbol":9,"members":[]}}}},{"isAttribute":false,"isHost":false,"isSelf":false,"isSkipSelf":false,"isOptional":false,"token":{"identifier":{"reference":{"__symbol":10,"members":[]}}}},{"isAttribute":false,"isHost":false,"isSelf":false,"isSkipSelf":false,"isOptional":false,"token":{"identifier":{"reference":{"__symbol":11,"members":[]}}}},{"isAttribute":false,"isHost":false,"isSelf":false,"isSkipSelf":false,"isOptional":false,"token":{"identifier":{"reference":{"__symbol":5,"members":[]}}}},{"isAttribute":false,"isHost":false,"isSelf":false,"isSkipSelf":false,"isOptional":false,"token":{"identifier":{"reference":{"__symbol":6,"members":[]}}}},{"isAttribute":false,"isHost":false,"isSelf":false,"isSkipSelf":false,"isOptional":false,"token":{"identifier":{"reference":{"__symbol":7,"members":[]}}}},{"isAttribute":false,"isHost":false,"isSelf":false,"isSkipSelf":false,"isOptional":false,"token":{"identifier":{"reference":{"__symbol":8,"members":[]}}}}],"lifecycleHooks":[1]},"isComponent":true,"selector":"page-divcharts","exportAs":null,"inputs":{},"outputs":{},"hostListeners":{},"hostProperties":{},"hostAttributes":{},"providers":[],"viewProviders":[],"queries":[],"guards":{},"viewQueries":[{"selectors":[{"value":"divChart"}],"first":true,"descendants":true,"propertyName":"divChart","read":null}],"entryComponents":[],"changeDetection":1,"template":{"ngContentSelectors":[],"encapsulation":2,"styles":[],"animations":[]},"componentViewType":{"__symbol":12,"members":[]},"rendererType":{"__symbol":13,"members":[]},"componentFactory":{"__symbol":14,"members":[]}}}],"symbols":[{"__symbol":0,"name":"DivchartsPage","filePath":"./divcharts"},{"__symbol":1,"name":"ViewChild","filePath":"@angular/core"},{"__symbol":2,"name":"Platform","filePath":"ionic-angular/umd/index"},{"__symbol":3,"name":"NavController","filePath":"ionic-angular/umd/index"},{"__symbol":4,"name":"NavParams","filePath":"ionic-angular/umd/index"},{"__symbol":5,"name":"AppRate","filePath":"@ionic-native/app-rate"},{"__symbol":6,"name":"ShareService","filePath":"../../app/share.service"},{"__symbol":7,"name":"HoroscopeService","filePath":"../../app/horoscope.service"},{"__symbol":8,"name":"Renderer2","filePath":"@angular/core"},{"__symbol":9,"name":"Platform","filePath":"ionic-angular/umd/platform/platform"},{"__symbol":10,"name":"NavController","filePath":"ionic-angular/umd/navigation/nav-controller"},{"__symbol":11,"name":"NavParams","filePath":"ionic-angular/umd/navigation/nav-params"},{"__symbol":12,"name":"View_DivchartsPage_0","filePath":"./divcharts.ngfactory"},{"__symbol":13,"name":"RenderType_DivchartsPage","filePath":"./divcharts.ngfactory"},{"__symbol":14,"name":"DivchartsPageNgFactory","filePath":"./divcharts.ngfactory"}]}